owapi/__init__.py
owapi/owapi.py
owapi-0.0.1.dist-info/LICENSE
owapi-0.0.1.dist-info/METADATA
owapi-0.0.1.dist-info/WHEEL
owapi-0.0.1.dist-info/top_level.txt
owapi-0.0.1.dist-info/zip-safe
owapi-0.0.1.dist-info/RECORD
